multidim_image_augmentation/__init__.py
multidim_image_augmentation/deformation_utils.py
multidim_image_augmentation/python/__init__.py
multidim_image_augmentation/python/ops/_augmentation_ops.so
multidim_image_augmentation/python/ops/__init__.py
multidim_image_augmentation/python/ops/augmentation_ops.py
image_augmentation-0.0.4.dist-info/WHEEL
image_augmentation-0.0.4.dist-info/RECORD
image_augmentation-0.0.4.dist-info/top_level.txt
image_augmentation-0.0.4.dist-info/LICENSE
image_augmentation-0.0.4.dist-info/METADATA
